{"cameraMode":{"drawMode":0,"name":"Shaded","section":"Shading Mode"},"sceneLighting":true,"audioPlay":false,"sceneViewState":{"showFog":true,"showMaterialUpdate":false,"showSkybox":true,"showFlares":true,"showImageEffects":true,"showParticleSystems":true},"in2DMode":false,"pivot":{"x":-13.113568305969239,"y":5.648512363433838,"z":-24.72526741027832},"rotation":{"x":-0.28606730699539187,"y":-0.17917799949645997,"z":0.05454147607088089,"w":-0.939734697341919},"size":0.9814397096633911,"orthographic":false}