{"cameraMode":{"drawMode":0,"name":"Shaded","section":"Shading Mode"},"sceneLighting":false,"audioPlay":false,"sceneViewState":{"showFog":true,"showMaterialUpdate":false,"showSkybox":false,"showFlares":true,"showImageEffects":true,"showParticleSystems":true},"in2DMode":false,"pivot":{"x":0.11110538244247437,"y":-4.3958425521850588e-7,"z":1.1548399925231934e-7},"rotation":{"x":-0.06756957620382309,"y":0.7321223616600037,"z":-0.0733712911605835,"w":-0.6738849878311157},"size":1.2743229866027833,"orthographic":false}